Metadata-Version: 1.0
Name: whatapi
Version: 0.1.0
Summary: What.cd API
Home-page: https://github.com/isaaczafuta/whatapi
Author: Isaac Zafuta
Author-email: isaac@zafuta.com
License: Copyright (c) 2012, Isaac Zafuta
